alibabacloud_cloudcallcenter20200701/__init__.py
alibabacloud_cloudcallcenter20200701/client.py
alibabacloud_cloudcallcenter20200701/models/__init__.py
alibabacloud_cloudcallcenter20200701/models/_abort_campaign_request.py
alibabacloud_cloudcallcenter20200701/models/_abort_campaign_response.py
alibabacloud_cloudcallcenter20200701/models/_abort_campaign_response_body.py
alibabacloud_cloudcallcenter20200701/models/_abort_cases_request.py
alibabacloud_cloudcallcenter20200701/models/_abort_cases_response.py
alibabacloud_cloudcallcenter20200701/models/_abort_cases_response_body.py
alibabacloud_cloudcallcenter20200701/models/_abort_cases_shrink_request.py
alibabacloud_cloudcallcenter20200701/models/_campaign_detail.py
alibabacloud_cloudcallcenter20200701/models/_check_demo_instance_exists_response.py
alibabacloud_cloudcallcenter20200701/models/_check_demo_instance_exists_response_body.py
alibabacloud_cloudcallcenter20200701/models/_check_mqrole_assumption_authority_response.py
alibabacloud_cloudcallcenter20200701/models/_check_mqrole_assumption_authority_response_body.py
alibabacloud_cloudcallcenter20200701/models/_create_campaign_request.py
alibabacloud_cloudcallcenter20200701/models/_create_campaign_response.py
alibabacloud_cloudcallcenter20200701/models/_create_campaign_response_body.py
alibabacloud_cloudcallcenter20200701/models/_create_campaign_shrink_request.py
alibabacloud_cloudcallcenter20200701/models/_create_chat_media_url_request.py
alibabacloud_cloudcallcenter20200701/models/_create_chat_media_url_response.py
alibabacloud_cloudcallcenter20200701/models/_create_chat_media_url_response_body.py
alibabacloud_cloudcallcenter20200701/models/_create_corp_number_group_request.py
alibabacloud_cloudcallcenter20200701/models/_create_corp_number_group_response.py
alibabacloud_cloudcallcenter20200701/models/_create_corp_number_group_response_body.py
alibabacloud_cloudcallcenter20200701/models/_create_demo_instance_request.py
alibabacloud_cloudcallcenter20200701-1.1.0.dist-info/LICENSE
alibabacloud_cloudcallcenter20200701-1.1.0.dist-info/METADATA
alibabacloud_cloudcallcenter20200701-1.1.0.dist-info/WHEEL
alibabacloud_cloudcallcenter20200701-1.1.0.dist-info/top_level.txt
alibabacloud_cloudcallcenter20200701-1.1.0.dist-info/RECORD
